unbox/__init__.py
unbox/_acquire_builtin_names.py
unbox/base.py
unbox/missing_install_names.py
unbox/recipes.py
unbox/data/dflt_import_to_install_name_map.json
unbox/data/standard_lib_names/2.7.csv
unbox/data/standard_lib_names/3.5.csv
unbox/data/standard_lib_names/3.6.csv
unbox/data/standard_lib_names/3.7.csv
unbox/data/standard_lib_names/3.8.csv
unbox/data/standard_lib_names/3.9.csv
unbox-0.0.18.data/data/data/standard_lib_names/2.7.csv
unbox-0.0.18.data/data/data/standard_lib_names/3.5.csv
unbox-0.0.18.data/data/data/standard_lib_names/3.6.csv
unbox-0.0.18.data/data/data/standard_lib_names/3.7.csv
unbox-0.0.18.data/data/data/standard_lib_names/3.8.csv
unbox-0.0.18.data/data/data/standard_lib_names/3.9.csv
unbox-0.0.18.data/data/data/standard_lib_names/dflt_import_to_install_name_map.json
unbox-0.0.18.dist-info/LICENSE
unbox-0.0.18.dist-info/METADATA
unbox-0.0.18.dist-info/WHEEL
unbox-0.0.18.dist-info/top_level.txt
unbox-0.0.18.dist-info/RECORD
