Metadata-Version: 2.1
Name: unbox
Version: 0.0.18
Summary: Finding imports in code
Home-page: https://github.com/i2mint/unbox
Author: OtoSense
License: apache-2.0
Platform: any
Requires-Dist: findimports
Requires-Dist: dol
Requires-Dist: importlib-resources
Requires-Dist: config2py
Requires-Dist: py2store
